searchflow/__init__.py
searchflow/api.py
searchflow/connectors/__init__.py
searchflow/connectors/onedrive.py
searchflow/db/__init__.py
searchflow/db/chroma.py
searchflow/db/postgresql.py
searchflow/db/tables.py
searchflow/extract/__init__.py
searchflow/extract/extraction.py
searchflow/graphs/__init__.py
searchflow/graphs/checkpointer.py
searchflow/graphs/graph.py
searchflow/graphs/old_graph.py
searchflow/graphs/utils/nodes.py
searchflow/graphs/utils/prompts.py
searchflow/graphs/utils/state.py
searchflow/importers/__init__.py
searchflow/importers/chrome.py
searchflow/importers/unstructured.py
searchflow/importers/webscraper.py
searchflow/llm/__init__.py
searchflow/llm/llm.py
searchflow/logger.py
searchflow/main.py
searchflow/models/__init__.py
searchflow/models/documents.py
searchflow/ner/__init__.py
searchflow/ner/extract.py
searchflow/ner/models/entities.py
searchflow/streaming/__init__.py
searchflow/streaming/processor.py
searchflow-0.0.111.dist-info/LICENSE
searchflow-0.0.111.dist-info/METADATA
searchflow-0.0.111.dist-info/WHEEL
searchflow-0.0.111.dist-info/RECORD
