Metadata-Version: 2.1
Name: searchflow
Version: 0.0.111
Summary: An assistant helping you to index webpages into structured datasets.
License: MIT
Author: Ben Selleslagh
Author-email: ben@vectrix.ai
Requires-Python: >=3.11,<3.13
Classifier: License :: OSI Approved :: MIT License
Classifier: Programming Language :: Python :: 3
Classifier: Programming Language :: Python :: 3.11
Classifier: Programming Language :: Python :: 3.12
Requires-Dist: asyncpg (>=0.29.0,<0.30.0)
Requires-Dist: colorlog (>=6.8.2,<7.0.0)
Requires-Dist: fake-useragent (>=1.5.1,<2.0.0)
Requires-Dist: fastapi (>=0.111.0,<0.112.0)
Requires-Dist: greenlet (>=3.0.3,<4.0.0)
Requires-Dist: langchain (>=0.2.7,<0.3.0)
Requires-Dist: langchain-anthropic (>=0.1.23,<0.2.0)
Requires-Dist: langchain-cohere
Requires-Dist: langchain-community (>=0.2.7,<0.3.0)
Requires-Dist: langchain-openai (>=0.1.14,<0.2.0)
Requires-Dist: langchain-postgres (>=0.0.9,<0.0.10)
Requires-Dist: langgraph (>=0.2.14,<0.3.0)
Requires-Dist: langgraph-cli (>=0.1.48,<0.2.0)
Requires-Dist: o365 (>=2.0.36,<3.0.0)
Requires-Dist: poppler-utils (>=0.1.0,<0.2.0)
Requires-Dist: protobuf (>=4.21.6,<5.0.0)
Requires-Dist: psycopg-binary (>=3.2.1,<4.0.0)
Requires-Dist: psycopg2-binary (>=2.9.9,<3.0.0)
Requires-Dist: spider-client (>=0.0.69,<0.0.70)
Requires-Dist: streamlit (>=1.36.0,<2.0.0)
Requires-Dist: supabase (>=2.7.2,<3.0.0)
Requires-Dist: tiktoken (>=0.7.0,<0.8.0)
Requires-Dist: trafilatura (>=1.9.0,<2.0.0)
Requires-Dist: unstructured-client (>=0.25.5,<0.26.0)
Requires-Dist: unstructured[all-docs] (>=0.15.7,<0.16.0)
Requires-Dist: uvicorn (>=0.30.1,<0.31.0)
Requires-Dist: validators (>=0.28.1,<0.29.0)
